ttruth/Document.py
ttruth/GTElement.py
ttruth/Rect.py
ttruth/Table.py
ttruth/__init__.py
ttruth-1.0.dist-info/METADATA
ttruth-1.0.dist-info/WHEEL
ttruth-1.0.dist-info/top_level.txt
ttruth-1.0.dist-info/RECORD
