Metadata-Version: 2.1
Name: ttruth
Version: 1.0
Summary: Module for handling labelled XML files from T-Truth
Home-page: UNKNOWN
Author: Sohaib Zahid
Author-email: sohaib023@gmail.com
License: UNKNOWN
Platform: UNKNOWN
